tiny_api_client/__init__.py
tiny_api_client/mypy.py
tiny_api_client/py.typed
tiny_api_client-1.4.0.dist-info/LICENSE
tiny_api_client-1.4.0.dist-info/METADATA
tiny_api_client-1.4.0.dist-info/WHEEL
tiny_api_client-1.4.0.dist-info/top_level.txt
tiny_api_client-1.4.0.dist-info/RECORD
