Metadata-Version: 2.2
Name: tiny-api-client
Version: 1.4.0
Summary: The short and sweet way to create an API client
Author-email: Jacob Sánchez <jacobszpz@protonmail.com>
Project-URL: Repository, https://github.com/sanjacob/tiny-api-client
Project-URL: Bug Tracker, https://github.com/sanjacob/tiny-api-client/issues
Classifier: Development Status :: 5 - Production/Stable
Classifier: Topic :: Internet :: WWW/HTTP
Classifier: Programming Language :: Python :: 3.10
Classifier: Programming Language :: Python :: 3.11
Classifier: Programming Language :: Python :: 3.12
Classifier: License :: OSI Approved :: GNU Lesser General Public License v2 (LGPLv2)
Classifier: Intended Audience :: Developers
Classifier: Operating System :: OS Independent
Classifier: Topic :: Software Development :: Libraries
Requires-Python: >=3.10
License-File: LICENSE
Requires-Dist: requests
Requires-Dist: typing_extensions
Provides-Extra: test
Requires-Dist: pytest; extra == "test"
Requires-Dist: pytest-mock; extra == "test"
Requires-Dist: exceptiongroup; extra == "test"
Requires-Dist: mypy; extra == "test"
Provides-Extra: docs
Requires-Dist: sphinx; extra == "docs"
Requires-Dist: sphinx-rtd-theme; extra == "docs"
